haikubot/__init__.py
haikubot/api_config.py
haikubot/cli.py
haikubot/core.py
haikubot/version.py
haikubot-0.3.0.dist-info/METADATA
haikubot-0.3.0.dist-info/WHEEL
haikubot-0.3.0.dist-info/entry_points.txt
haikubot-0.3.0.dist-info/top_level.txt
haikubot-0.3.0.dist-info/RECORD
