Metadata-Version: 2.2
Name: haikubot
Version: 0.3.0
Summary: 从Bilibili视频生成俳句的命令行工具
Home-page: https://github.com/lgy112112/haikubot
Author: lgy112112
Author-email: lgy112112@gmail.com
Keywords: bilibili,haiku,audio,transcription,llm,asr
Classifier: Programming Language :: Python :: 3
Classifier: License :: OSI Approved :: MIT License
Classifier: Operating System :: OS Independent
Requires-Python: >=3.7
Requires-Dist: requests
Requires-Dist: dashscope
Requires-Dist: openai
Dynamic: author
Dynamic: author-email
Dynamic: classifier
Dynamic: description
Dynamic: description-content-type
Dynamic: home-page
Dynamic: keywords
Dynamic: requires-dist
Dynamic: requires-python
Dynamic: summary
